pylint_import_modules/__init__.py
pylint_import_modules-0.2.0.dist-info/AUTHORS
pylint_import_modules-0.2.0.dist-info/LICENSE
pylint_import_modules-0.2.0.dist-info/METADATA
pylint_import_modules-0.2.0.dist-info/WHEEL
pylint_import_modules-0.2.0.dist-info/pbr.json
pylint_import_modules-0.2.0.dist-info/top_level.txt
pylint_import_modules-0.2.0.dist-info/RECORD
